{
    "success": true,
    "data": {
        "id": 7963,
        "name": "Tyc",
        "exam_passed": false,
        "show_etiquette": false,
        "avatar": "https://img3.tapimg.com/avatars/fef93f162088732454ec242e7bb3ac0c.jpg?imageMogr2/auto-orient/strip/thumbnail/!300x300r/gravity/Center/crop/300x300/format/jpg/interlace/1/quality/80",
        "medium_avatar": "https://img3.tapimg.com/avatars/fef93f162088732454ec242e7bb3ac0c.jpg?imageMogr2/auto-orient/strip/thumbnail/!300x300r/gravity/Center/crop/300x300/format/jpg/interlace/1/quality/40",
        "nickname": "Tyc",
        "gender": "",
        "country": "",
        "intro": "",
        "loc": "HK",
        "store": "cn",
        "language": "zh_TW",
        "is_deactivated": false,
        "is_deleted": false,
        "is_silent": false,
        "stat": {
            "fans_count": 1,
            "following_count": 0,
            "following_developer_count": 5,
            "following_app_count": 339,
            "following_console_game_app_count": 0,
            "following_group_count": 0,
            "favorite_app_count": 3,
            "favorite_event_count": 0,
            "favorite_topic_count": 0,
            "favorite_video_count": 0,
            "favorite_story_count": 0,
            "voteup_count": 3,
            "votefunny_count": 0,
            "reserved_count": 56,
            "reserved_ios_count": 0,
            "reserved_android_count": 56,
            "played_count": 297,
            "cloud_game_played_count": 2,
            "spent_tips": "1172 小時",
            "played_spent": 4221540,
            "created_topic_count": 0,
            "created_post_count": 1,
            "created_video_count": 0,
            "created_album_count": 0,
            "created_story_count": 0,
            "created_review_count": 8,
            "created_moment_count": 0,
            "badges_count": 0,
            "forum_count": 8,
            "history_app_count": 71,
            "history_topic_count": 8,
            "history_video_count": 3,
            "created_days": 2078,
            "reserved_total_count": 56
        },
        "sharing": {
            "url": "https://www.taptap.com/user/7963",
            "title": "Tyc的个人主页 - TapTap 发现好游戏",
            "description": "",
            "image": {
                "url": "https://img3.tapimg.com/avatars/fef93f162088732454ec242e7bb3ac0c.jpg?imageView2/2/w/800/h/9999/q/80/format/jpg/interlace/1/ignore-error/1",
                "medium_url": "https://img3.tapimg.com/avatars/fef93f162088732454ec242e7bb3ac0c.jpg?imageView2/2/w/800/h/9999/q/80/format/jpg/interlace/1/ignore-error/1",
                "original_url": "https://img3.tapimg.com/avatars/fef93f162088732454ec242e7bb3ac0c.jpg",
                "original_format": "jpg",
                "color": "0xffffff"
            },
            "message_params": {
                "obj_type": "user",
                "obj_id": "7963"
            }
        },
        "log": {
            "page_view": {
                "web_url": "https://tap-snow.cn-beijing.log.aliyuncs.com/logstores/logs/track.gif",
                "params": {
                    "type": "pageView",
                    "APIVersion": "0.6.0",
                    "paramId": 7963,
                    "paramType": "userDetail"
                }
            },
            "follow": {
                "web_url": "https://tap-snow.cn-beijing.log.aliyuncs.com/logstores/logs/track.gif",
                "params": {
                    "type": "follow",
                    "APIVersion": "0.6.0",
                    "paramId": 7963,
                    "paramType": "userDetail"
                }
            },
            "unfollow": {
                "web_url": "https://tap-snow.cn-beijing.log.aliyuncs.com/logstores/logs/track.gif",
                "params": {
                    "type": "unfollow",
                    "APIVersion": "0.6.0",
                    "paramId": 7963,
                    "paramType": "userDetail"
                }
            }
        },
        "event_log": {
            "paramId": 7963,
            "paramType": "userDetail",
            "via": ""
        }
    }
}